tox_gh_matrix/__init__.py
tox_gh_matrix/plugin.py
tox_gh_matrix/version.py
tox_gh_matrix/version_utils.py
tox_gh_matrix-0.2.0.dist-info/LICENSE
tox_gh_matrix-0.2.0.dist-info/METADATA
tox_gh_matrix-0.2.0.dist-info/WHEEL
tox_gh_matrix-0.2.0.dist-info/entry_points.txt
tox_gh_matrix-0.2.0.dist-info/top_level.txt
tox_gh_matrix-0.2.0.dist-info/zip-safe
tox_gh_matrix-0.2.0.dist-info/RECORD
