Metadata-Version: 2.1
Name: tox-gh-matrix
Version: 0.2.0
Summary: Generate a GitHub workflow build matrix from the tox.ini envlist
Home-page: https://github.com/medmunds/tox-gh-matrix
Author: Mike Edmunds
Author-email: medmunds@gmail.com
Maintainer: Mike Edmunds
Maintainer-email: medmunds@gmail.com
License: MIT
Project-URL: Source, https://github.com/medmunds/tox-gh-matrix
Project-URL: Tracker, https://github.com/medmunds/tox-gh-matrix/issues
Keywords: virtual,environments,isolated,testing,github,workflow
Platform: any
Classifier: Development Status :: 4 - Beta
Classifier: Framework :: tox
Classifier: Intended Audience :: Developers
Classifier: License :: OSI Approved :: MIT License
Classifier: Operating System :: OS Independent
Classifier: Topic :: Software Development :: Testing
Classifier: Topic :: Software Development :: Libraries
Classifier: Topic :: Utilities
Classifier: Programming Language :: Python :: 3
Classifier: Programming Language :: Python :: 3.6
Classifier: Programming Language :: Python :: 3.7
Classifier: Programming Language :: Python :: 3.8
Classifier: Programming Language :: Python :: 3.9
Classifier: Programming Language :: Python :: 3.10
Requires-Python: >=3.6
License-File: LICENSE
Requires-Dist: tox (<4,>=3.15.2)
Provides-Extra: docs
Provides-Extra: testing
Requires-Dist: pytest (>=6.2.0) ; extra == 'testing'
Requires-Dist: pytest-cov (>=3.0.0) ; extra == 'testing'
Requires-Dist: pytest-mock (>=3.6.0) ; extra == 'testing'
Requires-Dist: pytest-xdist (>=2.3.0) ; extra == 'testing'
